layercake/__init__.py
layercake/__version__.py
layercake-0.4.0.dist-info/DESCRIPTION.rst
layercake-0.4.0.dist-info/METADATA
layercake-0.4.0.dist-info/RECORD
layercake-0.4.0.dist-info/WHEEL
layercake-0.4.0.dist-info/metadata.json
layercake-0.4.0.dist-info/namespace_packages.txt
layercake-0.4.0.dist-info/top_level.txt
