Metadata-Version: 1.1
Name: layercake
Version: 0.4.0
Summary: Configuration stack
Home-page: https://github.com/getslash/layercake
Author: Dror Levin
Author-email: spatz@psybear.com
License: BSD3
Platform: UNKNOWN
Classifier: Programming Language :: Python :: 3.5
Classifier: Programming Language :: Python :: 3.6
